{
  "updateTime": "2026-06-05 13:06:20",
  "timestamp": 1780635980,
  "market": {
    "index": "上证综指",
    "indexCode": "000001.SH",
    "price": "4076.12",
    "chg": "+0.45%"
  },
  "layers": [
    {
      "id": "L1",
      "name": "能源基建",
      "sub": "电网 / 特高压 / 电力设备",
      "color": "#E8740A",
      "stocks": [
        {
          "code": "159326",
          "name": "电网设备ETF",
          "sector": "电网",
          "held": true,
          "pick": false,
          "p": "2.09",
          "c": "-0.14%",
          "cv": -0.14,
          "pe": "-",
          "cap": "-",
          "signal": "neutral",
          "signalNote": "站上MA20；MACD绿柱；ADX=12.1(震荡市)；预期日波动±3.11%",
          "signalTime": "13:00",
          "confidence": "低"
        },
        {
          "code": "300390",
          "name": "天华新能",
          "sector": "锂电上游",
          "held": true,
          "pick": false,
          "p": "82.61",
          "c": "+4.93%",
          "cv": 4.93,
          "pe": "-",
          "cap": "-",
          "signal": "neutral",
          "signalNote": "数据不足，暂无信号",
          "signalTime": "13:00",
          "confidence": "低"
        }
      ],
      "avg": 2.4,
      "summary": "能源基建板块2只标的，方向不明确，保持观望。",
      "summaryTime": "13:00"
    },
    {
      "id": "L2",
      "name": "算力芯片",
      "sub": "GPU / HBM / 半导体材料 / 液冷 / 服务器",
      "color": "#E03B3B",
      "stocks": [
        {
          "code": "002409",
          "name": "雅克科技",
          "sector": "半导体材料",
          "held": true,
          "pick": true,
          "p": "117.44",
          "c": "-0.29%",
          "cv": -0.29,
          "pe": "-",
          "cap": "-",
          "signal": "neutral",
          "signalNote": "数据不足，暂无信号",
          "signalTime": "13:00",
          "confidence": "低"
        },
        {
          "code": "002837",
          "name": "英维克",
          "sector": "AI液冷",
          "held": true,
          "pick": true,
          "p": "67.4",
          "c": "-2.63%",
          "cv": -2.63,
          "pe": "-",
          "cap": "-",
          "signal": "neutral",
          "signalNote": "数据不足，暂无信号",
          "signalTime": "13:00",
          "confidence": "低"
        },
        {
          "code": "601138",
          "name": "工业富联",
          "sector": "AI服务器",
          "held": true,
          "pick": true,
          "p": "76.21",
          "c": "-2.98%",
          "cv": -2.98,
          "pe": "-",
          "cap": "-",
          "signal": "neutral",
          "signalNote": "数据不足，暂无信号",
          "signalTime": "13:00",
          "confidence": "低"
        },
        {
          "code": "301217",
          "name": "铜冠铜箔",
          "sector": "电子铜箔",
          "held": true,
          "pick": false,
          "p": "113.3",
          "c": "+3.23%",
          "cv": 3.23,
          "pe": "-",
          "cap": "-",
          "signal": "neutral",
          "signalNote": "数据不足，暂无信号",
          "signalTime": "13:00",
          "confidence": "低"
        },
        {
          "code": "688008",
          "name": "澜起科技",
          "sector": "DDR5+CXL",
          "held": false,
          "pick": false,
          "p": "249.05",
          "c": "-4.09%",
          "cv": -4.09,
          "pe": "-",
          "cap": "-",
          "signal": "neutral",
          "signalNote": "数据不足，暂无信号",
          "signalTime": "13:00",
          "confidence": "低"
        }
      ],
      "avg": -1.35,
      "summary": "算力芯片板块5只标的，方向不明确，保持观望。",
      "summaryTime": "13:00"
    },
    {
      "id": "L3",
      "name": "通信基建",
      "sub": "光模块 / CPO / 高速PCB / 海缆",
      "color": "#2B7FD4",
      "stocks": [
        {
          "code": "001389",
          "name": "广合科技",
          "sector": "高速PCB",
          "held": true,
          "pick": false,
          "p": "176.94",
          "c": "-3.1%",
          "cv": -3.1,
          "pe": "-",
          "cap": "-",
          "signal": "neutral",
          "signalNote": "数据不足，暂无信号",
          "signalTime": "13:00",
          "confidence": "低"
        },
        {
          "code": "300476",
          "name": "胜宏科技",
          "sector": "高多层PCB",
          "held": true,
          "pick": false,
          "p": "349.46",
          "c": "-4.71%",
          "cv": -4.71,
          "pe": "-",
          "cap": "-",
          "signal": "neutral",
          "signalNote": "数据不足，暂无信号",
          "signalTime": "13:00",
          "confidence": "低"
        },
        {
          "code": "600487",
          "name": "亨通光电",
          "sector": "光通信+海缆",
          "held": false,
          "pick": true,
          "p": "98.54",
          "c": "+0.68%",
          "cv": 0.68,
          "pe": "-",
          "cap": "-",
          "signal": "neutral",
          "signalNote": "数据不足，暂无信号",
          "signalTime": "13:00",
          "confidence": "低"
        }
      ],
      "avg": -2.38,
      "summary": "通信基建板块3只标的，方向不明确，保持观望。",
      "summaryTime": "13:00"
    },
    {
      "id": "L4",
      "name": "模型层",
      "sub": "大模型 / 训练框架 / AI原生应用",
      "color": "#8E44AD",
      "stocks": [
        {
          "code": "300418",
          "name": "昆仑万维",
          "sector": "AI应用/大模型",
          "held": true,
          "pick": false,
          "p": "40.43",
          "c": "-0.12%",
          "cv": -0.12,
          "pe": "-",
          "cap": "-",
          "signal": "neutral",
          "signalNote": "数据不足，暂无信号",
          "signalTime": "13:00",
          "confidence": "低"
        }
      ],
      "avg": -0.12,
      "summary": "模型层板块1只标的，方向不明确，保持观望。",
      "summaryTime": "13:00"
    },
    {
      "id": "L5",
      "name": "应用层",
      "sub": "SaaS+AI / 互联网平台 / 消费科技",
      "color": "#0EA352",
      "stocks": [
        {
          "code": "HK.01810",
          "name": "小米集团-W",
          "sector": "港股互联网",
          "held": true,
          "pick": false,
          "p": "28.2",
          "c": "-0.63%",
          "cv": -0.63,
          "pe": "-",
          "cap": "-",
          "signal": "risk",
          "signalNote": "空头排列；跌破MA60；RSI偏低(30.9)；预期日波动±3.75%",
          "signalTime": "13:00",
          "confidence": "低"
        },
        {
          "code": "HK.03690",
          "name": "美团-W",
          "sector": "港股互联网",
          "held": true,
          "pick": false,
          "p": "79.45",
          "c": "+1.08%",
          "cv": 1.08,
          "pe": "-",
          "cap": "-",
          "signal": "neutral",
          "signalNote": "跌破MA20；跌破MA60；MACD绿柱；ADX=13.3(震荡市)；预期日波动±4.76%(高)",
          "signalTime": "13:00",
          "confidence": "低"
        },
        {
          "code": "HK.09988",
          "name": "阿里巴巴-W",
          "sector": "港股互联网",
          "held": true,
          "pick": false,
          "p": "123.3",
          "c": "-0.16%",
          "cv": -0.16,
          "pe": "-",
          "cap": "-",
          "signal": "neutral",
          "signalNote": "跌破MA20；跌破MA60；MACD绿柱；ADX=11.5(震荡市)；预期日波动±3.77%",
          "signalTime": "13:00",
          "confidence": "低"
        },
        {
          "code": "HK.01024",
          "name": "快手-W",
          "sector": "港股互联网",
          "held": true,
          "pick": false,
          "p": "47.28",
          "c": "+0.72%",
          "cv": 0.72,
          "pe": "-",
          "cap": "-",
          "signal": "neutral",
          "signalNote": "跌破MA20；跌破MA60；MACD红柱；ADX=9.2(震荡市)；预期日波动±4.57%(高)",
          "signalTime": "13:00",
          "confidence": "低"
        },
        {
          "code": "HK.01093",
          "name": "石药集团",
          "sector": "港股医药",
          "held": true,
          "pick": false,
          "p": "7.21",
          "c": "-0.41%",
          "cv": -0.41,
          "pe": "-",
          "cap": "-",
          "signal": "risk",
          "signalNote": "跌破MA20；跌破MA60；MACD红柱；ADX=37.0(强趋势)；预期日波动±5.53%(高)",
          "signalTime": "13:00",
          "confidence": "低"
        }
      ],
      "avg": 0.12,
      "summary": "应用层板块5只标的，整体偏弱（2只风险信号）。",
      "summaryTime": "13:00"
    }
  ],
  "etfs": [
    {
      "code": "512890",
      "name": "红利低波ETF",
      "sector": "防御",
      "p": "1.16",
      "c": "+0.52%",
      "cv": 0.52,
      "signal": "risk",
      "signalNote": "跌破MA20；跌破MA60；MACD红柱；ADX=30.4(强趋势)；预期日波动±1.12%(低)",
      "signalTime": "13:00",
      "confidence": "低"
    },
    {
      "code": "159363",
      "name": "创业板AI ETF",
      "sector": "AI赛道",
      "p": "1.45",
      "c": "-0.68%",
      "cv": -0.68,
      "signal": "buy",
      "signalNote": "多头排列；MACD红柱；预期日波动±4.1%(高)",
      "signalTime": "13:00",
      "confidence": "低"
    },
    {
      "code": "516510",
      "name": "云计算ETF",
      "sector": "AI云",
      "p": "1.77",
      "c": "-0.11%",
      "cv": -0.11,
      "signal": "neutral",
      "signalNote": "空头排列；跌破MA60；MACD绿柱；ADX=11.1(震荡市)；预期日波动±3.55%",
      "signalTime": "13:00",
      "confidence": "低"
    },
    {
      "code": "159326",
      "name": "电网设备ETF",
      "sector": "电网",
      "p": "2.09",
      "c": "-0.14%",
      "cv": -0.14,
      "signal": "neutral",
      "signalNote": "站上MA20；MACD绿柱；ADX=12.1(震荡市)；预期日波动±3.11%",
      "signalTime": "13:00",
      "confidence": "低"
    },
    {
      "code": "159338",
      "name": "中证A500ETF",
      "sector": "宽基",
      "p": "1.3",
      "c": "+0.15%",
      "cv": 0.15,
      "signal": "risk",
      "signalNote": "跌破MA20；MACD绿柱；预期日波动±1.93%(低)",
      "signalTime": "13:00",
      "confidence": "低"
    },
    {
      "code": "516630",
      "name": "云计ETF",
      "sector": "AI云",
      "p": "1.73",
      "c": "-0.17%",
      "cv": -0.17,
      "signal": "neutral",
      "signalNote": "空头排列；跌破MA60；MACD绿柱；ADX=10.2(震荡市)；预期日波动±3.46%",
      "signalTime": "13:00",
      "confidence": "低"
    },
    {
      "code": "159246",
      "name": "创业板AI ETF",
      "sector": "AI赛道",
      "p": "1.37",
      "c": "-0.72%",
      "cv": -0.72,
      "signal": "buy",
      "signalNote": "多头排列；MACD红柱；预期日波动±4.06%(高)",
      "signalTime": "13:00",
      "confidence": "低"
    },
    {
      "code": "560390",
      "name": "电网设备ETF",
      "sector": "电网",
      "p": "1.07",
      "c": "0.0%",
      "cv": 0.0,
      "signal": "neutral",
      "signalNote": "站上MA20；MACD绿柱；ADX=13.1(震荡市)；预期日波动±3.08%",
      "signalTime": "13:00",
      "confidence": "低"
    },
    {
      "code": "159516",
      "name": "半导体设备ETF国泰",
      "sector": "半导体设备",
      "p": "1.23",
      "c": "-0.8%",
      "cv": -0.8,
      "signal": "neutral",
      "signalNote": "站上MA20；MACD绿柱；ADX=40.8(强趋势)；预期日波动±6.6%(高)",
      "signalTime": "13:00",
      "confidence": "低"
    },
    {
      "code": "515880",
      "name": "通信ETF国泰",
      "sector": "通信设备",
      "p": "1.72",
      "c": "+0.7%",
      "cv": 0.7,
      "signal": "buy",
      "signalNote": "多头排列；RSI偏高(67.0)；MACD红柱；预期日波动±4.51%(高)",
      "signalTime": "13:00",
      "confidence": "低"
    }
  ],
  "hk": [
    {
      "code": "HK.01810",
      "name": "小米集团-W",
      "sector": "港股互联网",
      "held": true,
      "pick": false,
      "p": "28.2",
      "c": "-0.63%",
      "cv": -0.63,
      "pe": "-",
      "cap": "-",
      "signal": "risk",
      "signalNote": "空头排列；跌破MA60；RSI偏低(30.9)；预期日波动±3.75%",
      "signalTime": "13:00",
      "confidence": "低"
    },
    {
      "code": "HK.03690",
      "name": "美团-W",
      "sector": "港股互联网",
      "held": true,
      "pick": false,
      "p": "79.45",
      "c": "+1.08%",
      "cv": 1.08,
      "pe": "-",
      "cap": "-",
      "signal": "neutral",
      "signalNote": "跌破MA20；跌破MA60；MACD绿柱；ADX=13.3(震荡市)；预期日波动±4.76%(高)",
      "signalTime": "13:00",
      "confidence": "低"
    },
    {
      "code": "HK.09988",
      "name": "阿里巴巴-W",
      "sector": "港股互联网",
      "held": true,
      "pick": false,
      "p": "123.3",
      "c": "-0.16%",
      "cv": -0.16,
      "pe": "-",
      "cap": "-",
      "signal": "neutral",
      "signalNote": "跌破MA20；跌破MA60；MACD绿柱；ADX=11.5(震荡市)；预期日波动±3.77%",
      "signalTime": "13:00",
      "confidence": "低"
    },
    {
      "code": "HK.01024",
      "name": "快手-W",
      "sector": "港股互联网",
      "held": true,
      "pick": false,
      "p": "47.28",
      "c": "+0.72%",
      "cv": 0.72,
      "pe": "-",
      "cap": "-",
      "signal": "neutral",
      "signalNote": "跌破MA20；跌破MA60；MACD红柱；ADX=9.2(震荡市)；预期日波动±4.57%(高)",
      "signalTime": "13:00",
      "confidence": "低"
    },
    {
      "code": "HK.01093",
      "name": "石药集团",
      "sector": "港股医药",
      "held": true,
      "pick": false,
      "p": "7.21",
      "c": "-0.41%",
      "cv": -0.41,
      "pe": "-",
      "cap": "-",
      "signal": "risk",
      "signalNote": "跌破MA20；跌破MA60；MACD红柱；ADX=37.0(强趋势)；预期日波动±5.53%(高)",
      "signalTime": "13:00",
      "confidence": "低"
    }
  ],
  "signalUpdateTime": "2026-06-05 13:00:47"
}